{
    "User": "GMW",
    "Valid_Since": "2017-01-17 08:00:00",
    "Modified_At": "2018-01-18 14:22:00",
    "Frontend": ["HJ56-ECE", "HJ56-ECE"],
    "Band": [0, 1],
    "RotAttenuator_dB": [-10.0, -10.0],
    "FixedAttenuator_dB": [-3.0, -3.0],
    "Sampling_Rate_KHz": 50.0,
    "General_Remarks": "DC-offset problems, no post-det. amp.",
    "Channels": [
       {"ADC_CH_NAME": "ECEFAST01",
        "BAND": 0.0,
        "IF": 2.500,
        "BW": 1.000,
        "RF": 58.500,
        "RF_BW": [58.000, 59.000],
        "DETAILS":{            
            "BackEnd_RFAtt_dB": 0.0,
            "BackEnd_RFGain_dB": 42.4,
            "VideoGain_dB": 10.0,
            "DCOffset_V": 0.0,
            "Amplification_VV": 1.0,
            "Coupling": "DC",
            "HPF_Frequency_KHz": 0.0,
            "LPF_Frequency_KHz": 0.0,
            "Remark": "56 GHz LO, PORT11.5"} },
       {"ADC_CH_NAME": "ECEFAST02",
        "BAND": 0.0,
        "IF": 4.500,
        "BW": 1.000,
        "RF": 60.500,
        "RF_BW": [60.000, 61.000],
        "DETAILS":{            
            "BackEnd_RFAtt_dB": -3.0,
            "BackEnd_RFGain_dB": 42.4,
            "VideoGain_dB": 10.0,
            "DCOffset_V": 0.0,
            "Amplification_VV": 1.0,
            "Coupling": "DC",
            "HPF_Frequency_KHz": 0.0,
            "LPF_Frequency_KHz": 0.0,
            "Remark": "56 GHz LO, PORT11.5"} },
       {"ADC_CH_NAME": "ECEFAST03",
        "BAND": 0.0,
        "IF": 6.500,
        "BW": 1.000,
        "RF": 62.500,
        "RF_BW": [62.000, 63.000],
        "DETAILS":{            
            "BackEnd_RFAtt_dB": 0.0,
            "BackEnd_RFGain_dB": 42.4,
            "VideoGain_dB": 10.0,
            "DCOffset_V": 0.0,
            "Amplification_VV": 1.0,
            "Coupling": "DC",
            "HPF_Frequency_KHz": 0.0,
            "LPF_Frequency_KHz": 0.0,
            "Remark": "56 GHz LO, PORT11.5"} },
       {"ADC_CH_NAME": "ECEFAST04",
        "BAND": 0.0,
        "IF": 8.500,
        "BW": 1.000,
        "RF": 64.500,
        "RF_BW": [64.000, 65.000],
        "DETAILS":{            
            "BackEnd_RFAtt_dB": 0.0,
            "BackEnd_RFGain_dB": 42.4,
            "VideoGain_dB": 10.0,
            "DCOffset_V": 0.0,
            "Amplification_VV": 1.0,
            "Coupling": "DC",
            "HPF_Frequency_KHz": 0.0,
            "LPF_Frequency_KHz": 0.0,
            "Remark": "56 GHz LO, PORT11.5"} },
       {"ADC_CH_NAME": "ECEFAST05",
        "BAND": 0.0,
        "IF": 10.500,
        "BW": 1.000,
        "RF": 66.500,
        "RF_BW": [66.000, 67.000],
        "DETAILS":{            
            "BackEnd_RFAtt_dB": 0.0,
            "BackEnd_RFGain_dB": 42.4,
            "VideoGain_dB": 10.0,
            "DCOffset_V": 0.0,
            "Amplification_VV": 1.0,
            "Coupling": "DC",
            "HPF_Frequency_KHz": 0.0,
            "LPF_Frequency_KHz": 0.0,
            "Remark": "56 GHz LO, PORT11.5"} },
       {"ADC_CH_NAME": "ECEFAST06",
        "BAND": 0.0,
        "IF": 12.500,
        "BW": 1.000,
        "RF": 68.500,
        "RF_BW": [68.000, 69.000],
        "DETAILS":{            
            "BackEnd_RFAtt_dB": 0.0,
            "BackEnd_RFGain_dB": 42.4,
            "VideoGain_dB": 10.0,
            "DCOffset_V": 0.0,
            "Amplification_VV": 1.0,
            "Coupling": "DC",
            "HPF_Frequency_KHz": 0.0,
            "LPF_Frequency_KHz": 0.0,
            "Remark": "56 GHz LO, PORT11.5"} },
       {"ADC_CH_NAME": "ECEFAST07",
        "BAND": 0.0,
        "IF": 14.500,
        "BW": 1.000,
        "RF": 70.500,
        "RF_BW": [70.000, 71.000],
        "DETAILS":{            
            "BackEnd_RFAtt_dB": -10.0,
            "BackEnd_RFGain_dB": 42.4,
            "VideoGain_dB": 10.0,
            "DCOffset_V": 0.0,
            "Amplification_VV": 1.0,
            "Coupling": "DC",
            "HPF_Frequency_KHz": 0.0,
            "LPF_Frequency_KHz": 0.0,
            "Remark": "56 GHz LO, PORT11.5"} },
       {"ADC_CH_NAME": "ECEFAST08",
        "BAND": 0.0,
        "IF": 16.500,
        "BW": 1.000,
        "RF": 72.500,
        "RF_BW": [72.000, 73.000],
        "DETAILS":{            
            "BackEnd_RFAtt_dB": -3.0,
            "BackEnd_RFGain_dB": 42.4,
            "VideoGain_dB": 10.0,
            "DCOffset_V": 0.0,
            "Amplification_VV": 1.0,
            "Coupling": "DC",
            "HPF_Frequency_KHz": 0.0,
            "LPF_Frequency_KHz": 0.0,
            "Remark": "56 GHz LO, PORT11.5"} },
       {"ADC_CH_NAME": "ECEFAST09",
        "BAND": 1.0,
        "IF": 3.500,
        "BW": 1.000,
        "RF": 59.500,
        "RF_BW": [55.000, 60.000],
        "DETAILS":{           
            "BackEnd_RFAtt_dB": -3.0,
            "BackEnd_RFGain_dB": 36.7,
            "VideoGain_dB": 20.0,
            "DCOffset_V": 0.0,
            "Amplification_VV": 1.0,
            "Coupling": "DC",
            "HPF_Frequency_KHz": 0.0,
            "LPF_Frequency_KHz": 0.0,
            "Remark": "56 GHz LO, PORT11.5"} },
       {"ADC_CH_NAME": "ECEFAST10",
        "BAND": 1.0,
        "IF": 5.500,
        "BW": 1.000,
        "RF": 61.500,
        "RF_BW": [61.000, 62.000],
        "DETAILS":{            
            "BackEnd_RFAtt_dB": 0.0,
            "BackEnd_RFGain_dB": 36.7,
            "VideoGain_dB": 20.0,
            "DCOffset_V": 0.0,
            "Amplification_VV": 1.0,
            "Coupling": "DC",
            "HPF_Frequency_KHz": 0.0,
            "LPF_Frequency_KHz": 0.0,
            "Remark": "56 GHz LO, PORT11.5"} },
       {"ADC_CH_NAME": "ECEFAST11",
        "BAND": 1.0,
        "IF": 7.500,
        "BW": 1.000,
        "RF": 63.500,
        "RF_BW": [63.000, 64.000],
        "DETAILS":{
            "BackEnd_RFAtt_dB": 0.0,
            "BackEnd_RFGain_dB": 36.7,
            "VideoGain_dB": 20.0,
            "DCOffset_V": 0.0,
            "Amplification_VV": 1.0,
            "Coupling": "DC",
            "HPF_Frequency_KHz": 0.0,
            "LPF_Frequency_KHz": 0.0,
            "Remark": "56 GHz LO, PORT11.5"} },
       {"ADC_CH_NAME": "ECEFAST12",
        "BAND": 1.0,
        "IF": 9.500,
        "BW": 1.000,
        "RF": 65.500,
        "RF_BW": [65.000, 66.000],
        "DETAILS":{            
            "BackEnd_RFAtt_dB": 0.0,
            "BackEnd_RFGain_dB": 36.7,
            "VideoGain_dB": 20.0,
            "DCOffset_V": 0.0,
            "Amplification_VV": 1.0,
            "Coupling": "DC",
            "HPF_Frequency_KHz": 0.0,
            "LPF_Frequency_KHz": 0.0,
            "Remark": "56 GHz LO, PORT11.5"} },
       {"ADC_CH_NAME": "ECEFAST13",
        "BAND": 1.0,
        "IF": 11.500,
        "BW": 1.000,
        "RF": 67.500,
        "RF_BW": [67.000, 68.000],
        "DETAILS":{            
            "BackEnd_RFAtt_dB": 0.0,
            "BackEnd_RFGain_dB": 36.7,
            "VideoGain_dB": 20.0,
            "DCOffset_V": 0.0,
            "Amplification_VV": 1.0,
            "Coupling": "DC",
            "HPF_Frequency_KHz": 0.0,
            "LPF_Frequency_KHz": 0.0,
            "Remark": "56 GHz LO, PORT11.5"} },
       {"ADC_CH_NAME": "ECEFAST14",
        "BAND": 1.0,
        "IF": 13.500,
        "BW": 1.000,
        "RF": 69.500,
        "RF_BW": [69.000, 70.000],
        "DETAILS":{
            "BackEnd_RFAtt_dB": -3.0,
            "BackEnd_RFGain_dB": 36.7,
            "VideoGain_dB": 20.0,
            "DCOffset_V": 0.0,
            "Amplification_VV": 1.0,
            "Coupling": "DC",
            "HPF_Frequency_KHz": 0.0,
            "LPF_Frequency_KHz": 0.0,
            "Remark": "56 GHz LO, PORT11.5"} },
       {"ADC_CH_NAME": "ECEFAST15",
        "BAND": 1.0,
        "IF": 15.500,
        "BW": 1.000,
        "RF": 71.500,
        "RF_BW": [71.000, 72.000],
        "DETAILS":{            
            "BackEnd_RFAtt_dB": -3.0,
            "BackEnd_RFGain_dB": 36.7,
            "VideoGain_dB": 20.0,
            "DCOffset_V": 0.0,
            "Amplification_VV": 1.0,
            "Coupling": "DC",
            "HPF_Frequency_KHz": 0.0,
            "LPF_Frequency_KHz": 0.0,
            "Remark": "56 GHz LO, PORT11.5"} },
       {"ADC_CH_NAME": "ECEFAST16",
        "BAND": 1.0,
        "IF": 17.500,
        "BW": 1.000,
        "RF": 73.500,
        "RF_BW": [73.000, 74.000],
        "DETAILS":{            
            "BackEnd_RFAtt_dB": -3.0,
            "BackEnd_RFGain_dB": 36.7,
            "VideoGain_dB": 20.0,
            "DCOffset_V": 0.0,
            "Amplification_VV": 1.0,
            "Coupling": "DC",
            "HPF_Frequency_KHz": 0.0,
            "LPF_Frequency_KHz": 0.0,
            "Remark": "56 GHz LO, PORT11.5"} } 
    ]
}
